README
setup.py
pp_tinymce/__init__.py
pypoly_plugin_tinymce.egg-info/PKG-INFO
pypoly_plugin_tinymce.egg-info/SOURCES.txt
pypoly_plugin_tinymce.egg-info/dependency_links.txt
pypoly_plugin_tinymce.egg-info/entry_points.txt
pypoly_plugin_tinymce.egg-info/not-zip-safe
pypoly_plugin_tinymce.egg-info/top_level.txt